balderplugin/junit/__init__.py
balderplugin/junit/_version.py
balderplugin/junit/plugin.py
balderplugin_junit-0.0.3.dist-info/LICENSE
balderplugin_junit-0.0.3.dist-info/METADATA
balderplugin_junit-0.0.3.dist-info/WHEEL
balderplugin_junit-0.0.3.dist-info/top_level.txt
balderplugin_junit-0.0.3.dist-info/RECORD
